{
  "hash": "538e97ae",
  "configHash": "c8e8f8eb",
  "lockfileHash": "2f86c364",
  "browserHash": "9716d8b5",
  "optimized": {
    "vue": {
      "src": "../../../node_modules/.pnpm/vue@3.5.13_typescript@5.5.4/node_modules/vue/dist/vue.runtime.esm-bundler.js",
      "file": "vue.js",
      "fileHash": "eb5ec800",
      "needsInterop": false
    },
    "vitepress > @vue/devtools-api": {
      "src": "../../../node_modules/.pnpm/@vue+devtools-api@7.7.1/node_modules/@vue/devtools-api/dist/index.js",
      "file": "vitepress___@vue_devtools-api.js",
      "fileHash": "a389a63c",
      "needsInterop": false
    },
    "vitepress > @vueuse/core": {
      "src": "../../../node_modules/.pnpm/@vueuse+core@12.5.0_typescript@5.5.4/node_modules/@vueuse/core/index.mjs",
      "file": "vitepress___@vueuse_core.js",
      "fileHash": "664c2d54",
      "needsInterop": false
    },
    "@element-plus/icons-vue": {
      "src": "../../../node_modules/.pnpm/@element-plus+icons-vue@2.3.1_vue@3.5.13_typescript@5.5.4_/node_modules/@element-plus/icons-vue/dist/index.js",
      "file": "@element-plus_icons-vue.js",
      "fileHash": "c43d803c",
      "needsInterop": false
    },
    "@vueuse/core": {
      "src": "../../../node_modules/.pnpm/@vueuse+core@10.11.1_vue@3.5.13_typescript@5.5.4_/node_modules/@vueuse/core/index.mjs",
      "file": "@vueuse_core.js",
      "fileHash": "132ee0d7",
      "needsInterop": false
    },
    "axios": {
      "src": "../../../node_modules/.pnpm/axios@1.7.9/node_modules/axios/index.js",
      "file": "axios.js",
      "fileHash": "44aadaa1",
      "needsInterop": false
    },
    "countup.js": {
      "src": "../../../node_modules/.pnpm/countup.js@2.8.0/node_modules/countup.js/dist/countUp.min.js",
      "file": "countup__js.js",
      "fileHash": "cc0011e3",
      "needsInterop": false
    },
    "dayjs": {
      "src": "../../../node_modules/.pnpm/dayjs@1.11.13/node_modules/dayjs/dayjs.min.js",
      "file": "dayjs.js",
      "fileHash": "7cfaeacc",
      "needsInterop": true
    },
    "echarts/charts": {
      "src": "../../../node_modules/.pnpm/echarts@5.6.0/node_modules/echarts/charts.js",
      "file": "echarts_charts.js",
      "fileHash": "e2b8bb6d",
      "needsInterop": false
    },
    "echarts/components": {
      "src": "../../../node_modules/.pnpm/echarts@5.6.0/node_modules/echarts/components.js",
      "file": "echarts_components.js",
      "fileHash": "1e9b4904",
      "needsInterop": false
    },
    "echarts/core": {
      "src": "../../../node_modules/.pnpm/echarts@5.6.0/node_modules/echarts/core.js",
      "file": "echarts_core.js",
      "fileHash": "7b32ae0f",
      "needsInterop": false
    },
    "echarts/features": {
      "src": "../../../node_modules/.pnpm/echarts@5.6.0/node_modules/echarts/features.js",
      "file": "echarts_features.js",
      "fileHash": "c1e834ae",
      "needsInterop": false
    },
    "echarts/renderers": {
      "src": "../../../node_modules/.pnpm/echarts@5.6.0/node_modules/echarts/renderers.js",
      "file": "echarts_renderers.js",
      "fileHash": "942c9fb0",
      "needsInterop": false
    },
    "element-plus": {
      "src": "../../../node_modules/.pnpm/element-plus@2.9.4_vue@3.5.13_typescript@5.5.4_/node_modules/element-plus/es/index.mjs",
      "file": "element-plus.js",
      "fileHash": "df294dc8",
      "needsInterop": false
    },
    "element-plus/dist/locale/en.mjs": {
      "src": "../../../node_modules/.pnpm/element-plus@2.9.4_vue@3.5.13_typescript@5.5.4_/node_modules/element-plus/dist/locale/en.mjs",
      "file": "element-plus_dist_locale_en__mjs.js",
      "fileHash": "e0cda2ac",
      "needsInterop": false
    },
    "element-plus/dist/locale/ja.mjs": {
      "src": "../../../node_modules/.pnpm/element-plus@2.9.4_vue@3.5.13_typescript@5.5.4_/node_modules/element-plus/dist/locale/ja.mjs",
      "file": "element-plus_dist_locale_ja__mjs.js",
      "fileHash": "7ebe4329",
      "needsInterop": false
    },
    "element-plus/dist/locale/zh-cn.mjs": {
      "src": "../../../node_modules/.pnpm/element-plus@2.9.4_vue@3.5.13_typescript@5.5.4_/node_modules/element-plus/dist/locale/zh-cn.mjs",
      "file": "element-plus_dist_locale_zh-cn__mjs.js",
      "fileHash": "834cdf45",
      "needsInterop": false
    },
    "element-plus/dist/locale/zh-tw.mjs": {
      "src": "../../../node_modules/.pnpm/element-plus@2.9.4_vue@3.5.13_typescript@5.5.4_/node_modules/element-plus/dist/locale/zh-tw.mjs",
      "file": "element-plus_dist_locale_zh-tw__mjs.js",
      "fileHash": "90257315",
      "needsInterop": false
    },
    "element-plus/es/components/table/src/table/defaults.mjs": {
      "src": "../../../node_modules/.pnpm/element-plus@2.9.4_vue@3.5.13_typescript@5.5.4_/node_modules/element-plus/es/components/table/src/table/defaults.mjs",
      "file": "element-plus_es_components_table_src_table_defaults__mjs.js",
      "fileHash": "0d6d6b12",
      "needsInterop": false
    },
    "exceljs": {
      "src": "../../../node_modules/.pnpm/exceljs@4.4.0/node_modules/exceljs/dist/exceljs.min.js",
      "file": "exceljs.js",
      "fileHash": "a6964403",
      "needsInterop": true
    },
    "file-saver": {
      "src": "../../../node_modules/.pnpm/file-saver@2.0.5/node_modules/file-saver/dist/FileSaver.min.js",
      "file": "file-saver.js",
      "fileHash": "fc3b547f",
      "needsInterop": true
    },
    "filesize": {
      "src": "../../../node_modules/.pnpm/filesize@10.1.6/node_modules/filesize/dist/filesize.esm.js",
      "file": "filesize.js",
      "fileHash": "92adf4eb",
      "needsInterop": false
    },
    "lodash-es": {
      "src": "../../../node_modules/.pnpm/lodash-es@4.17.21/node_modules/lodash-es/lodash.js",
      "file": "lodash-es.js",
      "fileHash": "9d90c19b",
      "needsInterop": false
    },
    "nprogress": {
      "src": "../../../node_modules/.pnpm/nprogress@0.2.0/node_modules/nprogress/nprogress.js",
      "file": "nprogress.js",
      "fileHash": "850b69f9",
      "needsInterop": true
    },
    "pinia": {
      "src": "../../../node_modules/.pnpm/pinia@2.3.1_typescript@5.5.4_vue@3.5.13_typescript@5.5.4_/node_modules/pinia/dist/pinia.mjs",
      "file": "pinia.js",
      "fileHash": "c9d77544",
      "needsInterop": false
    },
    "sortablejs": {
      "src": "../../../node_modules/.pnpm/sortablejs@1.15.6/node_modules/sortablejs/modular/sortable.esm.js",
      "file": "sortablejs.js",
      "fileHash": "a3ccd5f1",
      "needsInterop": false
    },
    "uuid": {
      "src": "../../../node_modules/.pnpm/uuid@10.0.0/node_modules/uuid/dist/esm-browser/index.js",
      "file": "uuid.js",
      "fileHash": "a4803f90",
      "needsInterop": false
    },
    "vue-cropper": {
      "src": "../../../node_modules/.pnpm/vue-cropper@1.1.4/node_modules/vue-cropper/dist/vue-cropper.es.js",
      "file": "vue-cropper.js",
      "fileHash": "f5381328",
      "needsInterop": false
    },
    "vue-i18n": {
      "src": "../../../node_modules/.pnpm/vue-i18n@10.0.5_vue@3.5.13_typescript@5.5.4_/node_modules/vue-i18n/dist/vue-i18n.mjs",
      "file": "vue-i18n.js",
      "fileHash": "39104e0e",
      "needsInterop": false
    },
    "vue-router": {
      "src": "../../../node_modules/.pnpm/vue-router@4.5.0_vue@3.5.13_typescript@5.5.4_/node_modules/vue-router/dist/vue-router.mjs",
      "file": "vue-router.js",
      "fileHash": "57aeca46",
      "needsInterop": false
    },
    "@theme/index": {
      "src": "../../../node_modules/.pnpm/vitepress@1.6.3_@algolia+client-search@5.20.1_@types+node@22.13.1_async-validator@4.2.5_axios_3vymjx26b2iztijxcoic5ubb7i/node_modules/vitepress/dist/client/theme-default/index.js",
      "file": "@theme_index.js",
      "fileHash": "881bfccb",
      "needsInterop": false
    }
  },
  "chunks": {
    "chunk-CQ64OYRR": {
      "file": "chunk-CQ64OYRR.js"
    },
    "chunk-WHGCFFZJ": {
      "file": "chunk-WHGCFFZJ.js"
    },
    "chunk-YD2HXQFF": {
      "file": "chunk-YD2HXQFF.js"
    },
    "chunk-XJUXNFLZ": {
      "file": "chunk-XJUXNFLZ.js"
    },
    "chunk-OF6NYLRY": {
      "file": "chunk-OF6NYLRY.js"
    },
    "chunk-PKIG4N6E": {
      "file": "chunk-PKIG4N6E.js"
    },
    "chunk-J7IF3E3T": {
      "file": "chunk-J7IF3E3T.js"
    },
    "chunk-KCPF3Y3C": {
      "file": "chunk-KCPF3Y3C.js"
    },
    "chunk-LJNZEHHJ": {
      "file": "chunk-LJNZEHHJ.js"
    },
    "chunk-ZPB7DPDA": {
      "file": "chunk-ZPB7DPDA.js"
    },
    "chunk-6572SWEZ": {
      "file": "chunk-6572SWEZ.js"
    },
    "chunk-CXPDNTAW": {
      "file": "chunk-CXPDNTAW.js"
    },
    "chunk-2EUAXMBT": {
      "file": "chunk-2EUAXMBT.js"
    },
    "chunk-E47RNMA3": {
      "file": "chunk-E47RNMA3.js"
    },
    "chunk-DJW7UFYJ": {
      "file": "chunk-DJW7UFYJ.js"
    },
    "chunk-JLOPIRZS": {
      "file": "chunk-JLOPIRZS.js"
    },
    "chunk-PR4QN5HX": {
      "file": "chunk-PR4QN5HX.js"
    }
  }
}